[
  {
    "Title": "1.8 S",
    "C_merke": "ALPINE",
    "C_modell": "A110",
    "C_typ": "1.8 S",
    "yearRange": "2019 - 2024",
    "registeredCars": "5",
    "seats": "1-1",
    "imageUrl": "https://cdn.bilregistret.ai/compressed-mobile/Bilregistret-alpine-a110-2019-2024.webp",
    "high_res": "https://cdn.bilregistret.ai/high-res/bilregistret-alpine-a110-2019-2024.webp",
    "C_chassi": "",
    "C_bransle": "BENSIN",
    "C_kw": "215",
    "C_hk": "292",
    "C_slagvolym": "1800",
    "C_lit": "1.8",
    "C_cylinder": "4",
    "C_hjuldrift": "BAKHJULSDRIFT",
    "C_motorkod": "",
    "MINI_AR": "2019",
    "MAX_YEAR": "2024",
    "ar_fra": "2019",
    "ar_till": "2024",
    "HJUL_DRIFT_SAMLAD": "",
    "BRANSLE_SAMLAD": "",
    "C_kaross": "COUPE",
    "kaross_samlad": "",
    "tcount": "5",
    "t_count": "5",
    "description": "",
    "model description": "",
    "Mobile Image": "",
    "slug": "18-s"
  },
  {
    "Title": "1.8",
    "C_merke": "ALPINE",
    "C_modell": "A110",
    "C_typ": "1.8",
    "yearRange": "2017 - 2024",
    "registeredCars": "29",
    "seats": "1-1",
    "imageUrl": "https://cdn.bilregistret.ai/compressed-mobile/Bilregistret-alpine-a110-2017-2024.webp",
    "high_res": "https://cdn.bilregistret.ai/high-res/bilregistret-alpine-a110-2019-2024.webp",
    "C_chassi": "",
    "C_bransle": "BENSIN",
    "C_kw": "185",
    "C_hk": "252",
    "C_slagvolym": "1800",
    "C_lit": "1.8",
    "C_cylinder": "4",
    "C_hjuldrift": "BAKHJULSDRIFT",
    "C_motorkod": "",
    "MINI_AR": "2017",
    "MAX_YEAR": "2024",
    "ar_fra": "2017",
    "ar_till": "2024",
    "HJUL_DRIFT_SAMLAD": "",
    "BRANSLE_SAMLAD": "",
    "C_kaross": "COUPE",
    "kaross_samlad": "",
    "tcount": "29",
    "t_count": "29",
    "description": "",
    "model description": "",
    "Mobile Image": "",
    "slug": "18"
  },
  {
    "Title": "1.8 GT",
    "C_merke": "ALPINE",
    "C_modell": "A110",
    "C_typ": "1.8 GT",
    "yearRange": "2021 - 2024",
    "registeredCars": "16",
    "seats": "1-1",
    "imageUrl": "https://cdn.bilregistret.ai/compressed-mobile/Bilregistret-alpine-a110-2021-2024.webp",
    "high_res": "https://cdn.bilregistret.ai/high-res/bilregistret-alpine-a110-2019-2024.webp",
    "C_chassi": "",
    "C_bransle": "BENSIN",
    "C_kw": "221",
    "C_hk": "300",
    "C_slagvolym": "1800",
    "C_lit": "1.8",
    "C_cylinder": "4",
    "C_hjuldrift": "BAKHJULSDRIFT",
    "C_motorkod": "",
    "MINI_AR": "2021",
    "MAX_YEAR": "2024",
    "ar_fra": "2021",
    "ar_till": "2024",
    "HJUL_DRIFT_SAMLAD": "",
    "BRANSLE_SAMLAD": "",
    "C_kaross": "COUPE",
    "kaross_samlad": "",
    "tcount": "16",
    "t_count": "16",
    "description": "",
    "model description": "",
    "Mobile Image": "",
    "slug": "18-gt"
  }
]