[
  {
    "Title": "3.8",
    "C_merke": "BUICK",
    "C_modell": "LESABRE",
    "C_typ": "3.8",
    "yearRange": "1995 - 1999",
    "registeredCars": "18",
    "seats": "4-5",
    "imageUrl": "https://cdn.bilregistret.ai/compressed-mobile/Bilregistret-buick-lesabre-1995-1999.webp",
    "high_res": "https://cdn.bilregistret.ai/high-res/bilregistret-buick-lesabre-1995-1999.webp",
    "C_chassi": "",
    "C_bransle": "BENSIN",
    "C_kw": "153",
    "C_hk": "208",
    "C_slagvolym": "3800",
    "C_lit": "3.8",
    "C_cylinder": "8",
    "C_hjuldrift": "FRAMHJULSDRIFT",
    "C_motorkod": "",
    "MINI_AR": "1995",
    "MAX_YEAR": "1999",
    "ar_fra": "1995",
    "ar_till": "1999",
    "HJUL_DRIFT_SAMLAD": "",
    "BRANSLE_SAMLAD": "",
    "C_kaross": "SEDAN",
    "kaross_samlad": "",
    "tcount": "18",
    "t_count": "18",
    "description": "",
    "model description": "",
    "Mobile Image": "",
    "slug": "38"
  }
]