{
  "brand": {
    "id": "593",
    "merke_id": "125",
    "title": "Suzuki",
    "slug": "suzuki",
    "brandimage": "https://cdn.bilregistret.ai/brands/suzuki.png",
    "bannerimage": "https://cdn.bilregistret.ai/brands/suzuki-car.jpeg",
    "country_code": "Japan",
    "flags": "https://d220xhopowubtq.cloudfront.net/flags/Group.svg",
    "originalData": {
      "id": "593",
      "merke_id": "125",
      "title": "Suzuki",
      "slug": "suzuki",
      "brandimage": "https://cdn.bilregistret.ai/brands/suzuki.png",
      "bannerimage": "https://cdn.bilregistret.ai/brands/suzuki-car.jpeg",
      "country_code": "Japan",
      "flags": "https://d220xhopowubtq.cloudfront.net/flags/Group.svg",
      "brands_list": "/bil/",
      "brands_item": "/bil/suzuki",
      "view_count": "3"
    }
  },
  "model": {
    "id": "1645",
    "c_merke": "SUZUKI",
    "c_modell": "GRAND VITARA",
    "slug": "grand-vitara",
    "yearRange": "1998-2024",
    "registeredCars": "908",
    "seats": "1-4",
    "imageUrl": "https://cdn.bilregistret.ai/compressed-mobile/Bilregistret-suzuki-grand-vitara-2009-2024.webp",
    "fuelTypes": [
      "BENSIN",
      "DIESEL"
    ],
    "bodyTypes": [
      "CABRIOLET",
      "TERRÄNGBIL"
    ],
    "engineTypes": [
      "BAKHJULSDRIFT",
      "FYRHJULSDRIFT"
    ],
    "minYear": 1998,
    "maxYear": 2024,
    "originalData": {
      "ID": "1645",
      "C_merke": "SUZUKI",
      "C_modell": "GRAND VITARA",
      "slug": "grand-vitara",
      "modell_id": "30862",
      "MINI_AR": "1998",
      "MAX_YEAR": "2024",
      "t_count": "908",
      "Car Image": "https://cdn.bilregistret.ai/compressed-mobile/Bilregistret-suzuki-grand-vitara-2009-2024.webp",
      "high_res": "https://cdn.bilregistret.ai/high-res/bilregistret-suzuki-grand-vitara-2009-2024.webp",
      "BRANSLE_SAMLAD": "BENSIN, DIESEL",
      "kaross_samlad": "CABRIOLET, TERRÄNGBIL",
      "HJUL_DRIFT_SAMLAD": "BAKHJULSDRIFT, FYRHJULSDRIFT",
      "minSeats": "1",
      "maxSeats": "4"
    }
  },
  "subModels": [
    {
      "id": "1645",
      "modell_id": "30862",
      "c_merke": "SUZUKI",
      "c_modell": "GRAND VITARA",
      "c_typ": "2.4 Allhjulsdrift",
      "slug": "24-allhjulsdrift",
      "yearRange": "2009 - 2024",
      "registeredCars": "908",
      "seats": "1-4",
      "imageUrl": "https://cdn.bilregistret.ai/compressed-mobile/Bilregistret-suzuki-grand-vitara-2009-2024.webp",
      "C_chassi": "[JT, TE, TD]",
      "engine": "BENSIN",
      "originalData": {
        "ID": "1645",
        "submodel_title": "2-4-Allhjulsdrift-TERRANGBIL-JT-TE-TD-FYRHJULSDRIFT-124-kw",
        "modell_id": "30862",
        "C_merke": "SUZUKI",
        "C_modell": "GRAND VITARA",
        "C_typ": "2.4 Allhjulsdrift",
        "slug": "2.4-allhjulsdrift",
        "ar_fra": "2009",
        "ar_till": "2024",
        "t_count": "908",
        "Car Image": "https://cdn.bilregistret.ai/compressed-mobile/Bilregistret-suzuki-grand-vitara-2009-2024.webp",
        "high_res": "https://cdn.bilregistret.ai/high-res/bilregistret-suzuki-grand-vitara-2009-2024.webp",
        "C_chassi": "[JT, TE, TD]",
        "C_bransle": "BENSIN",
        "C_kaross": "TERRÄNGBIL",
        "C_hk": "169",
        "minSeats": "1",
        "maxSeats": "4"
      }
    },
    {
      "id": "9328",
      "modell_id": "30862",
      "c_merke": "SUZUKI",
      "c_modell": "GRAND VITARA",
      "c_typ": "2.4 Allhjulsdrift",
      "slug": "24-allhjulsdrift",
      "yearRange": "2009 - 2024",
      "registeredCars": "48",
      "seats": "1-3",
      "imageUrl": "https://cdn.bilregistret.ai/compressed-mobile/Bilregistret-suzuki-grand-vitara-2009-2024.webp",
      "C_chassi": "[JT, TE, TD]",
      "engine": "BENSIN",
      "originalData": {
        "ID": "9328",
        "submodel_title": "2-4-Allhjulsdrift-TERRANGBIL-JT-TE-TD-FYRHJULSDRIFT-122-kw",
        "modell_id": "30862",
        "C_merke": "SUZUKI",
        "C_modell": "GRAND VITARA",
        "C_typ": "2.4 Allhjulsdrift",
        "slug": "2.4-allhjulsdrift",
        "ar_fra": "2009",
        "ar_till": "2024",
        "t_count": "48",
        "Car Image": "https://cdn.bilregistret.ai/compressed-mobile/Bilregistret-suzuki-grand-vitara-2009-2024.webp",
        "high_res": "https://cdn.bilregistret.ai/high-res/bilregistret-suzuki-grand-vitara-2009-2024.webp",
        "C_chassi": "[JT, TE, TD]",
        "C_bransle": "BENSIN",
        "C_kaross": "TERRÄNGBIL",
        "C_hk": "166",
        "minSeats": "1",
        "maxSeats": "3"
      }
    },
    {
      "id": "2982",
      "modell_id": "30862",
      "c_merke": "SUZUKI",
      "c_modell": "GRAND VITARA",
      "c_typ": "1.6 Allhjulsdrift",
      "slug": "16-allhjulsdrift",
      "yearRange": "2005 - 2024",
      "registeredCars": "426",
      "seats": "1-4",
      "imageUrl": "https://cdn.bilregistret.ai/compressed-mobile/Bilregistret-suzuki-grand-vitara-2005-2024.webp",
      "C_chassi": "[JT, TE, TD]",
      "engine": "BENSIN",
      "originalData": {
        "ID": "2982",
        "submodel_title": "1-6-Allhjulsdrift-TERRANGBIL-JT-TE-TD-FYRHJULSDRIFT-78-kw",
        "modell_id": "30862",
        "C_merke": "SUZUKI",
        "C_modell": "GRAND VITARA",
        "C_typ": "1.6 Allhjulsdrift",
        "slug": "1.6-allhjulsdrift",
        "ar_fra": "2005",
        "ar_till": "2024",
        "t_count": "426",
        "Car Image": "https://cdn.bilregistret.ai/compressed-mobile/Bilregistret-suzuki-grand-vitara-2005-2024.webp",
        "high_res": "https://cdn.bilregistret.ai/high-res/bilregistret-suzuki-grand-vitara-2009-2024.webp",
        "C_chassi": "[JT, TE, TD]",
        "C_bransle": "BENSIN",
        "C_kaross": "TERRÄNGBIL",
        "C_hk": "106",
        "minSeats": "1",
        "maxSeats": "4"
      }
    },
    {
      "id": "2837",
      "modell_id": "30862",
      "c_merke": "SUZUKI",
      "c_modell": "GRAND VITARA",
      "c_typ": "1.9 Ddis Allhjulsdrift",
      "slug": "19-ddis-allhjulsdrift",
      "yearRange": "2005 - 2015",
      "registeredCars": "440",
      "seats": "1-4",
      "imageUrl": "https://cdn.bilregistret.ai/compressed-mobile/Bilregistret-suzuki-grand-vitara-2005-2015.webp",
      "C_chassi": "[JT, TE, TD]",
      "engine": "DIESEL",
      "originalData": {
        "ID": "2837",
        "submodel_title": "1-9-Ddis-Allhjulsdrift-TERRANGBIL-JT-TE-TD-FYRHJULSDRIFT-95-kw",
        "modell_id": "30862",
        "C_merke": "SUZUKI",
        "C_modell": "GRAND VITARA",
        "C_typ": "1.9 Ddis Allhjulsdrift",
        "slug": "1.9-ddis-allhjulsdrift",
        "ar_fra": "2005",
        "ar_till": "2015",
        "t_count": "440",
        "Car Image": "https://cdn.bilregistret.ai/compressed-mobile/Bilregistret-suzuki-grand-vitara-2005-2015.webp",
        "high_res": "https://cdn.bilregistret.ai/high-res/bilregistret-suzuki-grand-vitara-2009-2024.webp",
        "C_chassi": "[JT, TE, TD]",
        "C_bransle": "DIESEL",
        "C_kaross": "TERRÄNGBIL",
        "C_hk": "129",
        "minSeats": "1",
        "maxSeats": "4"
      }
    },
    {
      "id": "1453",
      "modell_id": "30862",
      "c_merke": "SUZUKI",
      "c_modell": "GRAND VITARA",
      "c_typ": "2.0 ALLHJULSDRIFT",
      "slug": "20-allhjulsdrift",
      "yearRange": "2005 - 2015",
      "registeredCars": "969",
      "seats": "1-4",
      "imageUrl": "https://cdn.bilregistret.ai/compressed-mobile/Bilregistret-suzuki-grand vitara-2005-2015.webp",
      "C_chassi": "[JT, TE, TD]",
      "engine": "BENSIN",
      "originalData": {
        "ID": "1453",
        "submodel_title": "2-0-ALLHJULSDRIFT-TERRANGBIL-JT-TE-TD-FYRHJULSDRIFT-103-kw",
        "modell_id": "30862",
        "C_merke": "SUZUKI",
        "C_modell": "GRAND VITARA",
        "C_typ": "2.0 ALLHJULSDRIFT",
        "slug": "2.0-allhjulsdrift",
        "ar_fra": "2005",
        "ar_till": "2015",
        "t_count": "969",
        "Car Image": "https://cdn.bilregistret.ai/compressed-mobile/Bilregistret-suzuki-grand vitara-2005-2015.webp",
        "high_res": "https://cdn.bilregistret.ai/high-res/bilregistret-suzuki-grand-vitara-2009-2024.webp",
        "C_chassi": "[JT, TE, TD]",
        "C_bransle": "BENSIN",
        "C_kaross": "TERRÄNGBIL",
        "C_hk": "140",
        "minSeats": "1",
        "maxSeats": "4"
      }
    },
    {
      "id": "13056",
      "modell_id": "30862",
      "c_merke": "SUZUKI",
      "c_modell": "GRAND VITARA",
      "c_typ": "3.2 Allhjulsdrift",
      "slug": "32-allhjulsdrift",
      "yearRange": "2009 - 2015",
      "registeredCars": "13",
      "seats": "4-4",
      "imageUrl": "https://cdn.bilregistret.ai/compressed-mobile/Bilregistret-suzuki-grand vitara-2009-2015.webp",
      "C_chassi": "[JT, TE, TD]",
      "engine": "BENSIN",
      "originalData": {
        "ID": "13056",
        "submodel_title": "3-2-Allhjulsdrift-TERRANGBIL-JT-TE-TD-FYRHJULSDRIFT-171-kw",
        "modell_id": "30862",
        "C_merke": "SUZUKI",
        "C_modell": "GRAND VITARA",
        "C_typ": "3.2 Allhjulsdrift",
        "slug": "3.2-allhjulsdrift",
        "ar_fra": "2009",
        "ar_till": "2015",
        "t_count": "13",
        "Car Image": "https://cdn.bilregistret.ai/compressed-mobile/Bilregistret-suzuki-grand vitara-2009-2015.webp",
        "high_res": "https://cdn.bilregistret.ai/high-res/bilregistret-suzuki-grand-vitara-2009-2024.webp",
        "C_chassi": "[JT, TE, TD]",
        "C_bransle": "BENSIN",
        "C_kaross": "TERRÄNGBIL",
        "C_hk": "233",
        "minSeats": "4",
        "maxSeats": "4"
      }
    },
    {
      "id": "18118",
      "modell_id": "30862",
      "c_merke": "SUZUKI",
      "c_modell": "GRAND VITARA",
      "c_typ": "2",
      "slug": "2",
      "yearRange": "2005 - 2015",
      "registeredCars": "1",
      "seats": "1-1",
      "imageUrl": "https://cdn.bilregistret.ai/compressed-mobile/Bilregistret-suzuki-grand-vitara-2005-2015.webp",
      "C_chassi": "[JT, TE, TD]",
      "engine": "BENSIN",
      "originalData": {
        "ID": "18118",
        "submodel_title": "2-0-TERRANGBIL-JT-TE-TD-BAKHJULSDRIFT-103-kw",
        "modell_id": "30862",
        "C_merke": "SUZUKI",
        "C_modell": "GRAND VITARA",
        "C_typ": "2",
        "slug": "2",
        "ar_fra": "2005",
        "ar_till": "2015",
        "t_count": "1",
        "Car Image": "https://cdn.bilregistret.ai/compressed-mobile/Bilregistret-suzuki-grand-vitara-2005-2015.webp",
        "high_res": "https://cdn.bilregistret.ai/high-res/bilregistret-suzuki-grand-vitara-2009-2024.webp",
        "C_chassi": "[JT, TE, TD]",
        "C_bransle": "BENSIN",
        "C_kaross": "TERRÄNGBIL",
        "C_hk": "140",
        "minSeats": "1",
        "maxSeats": "1"
      }
    },
    {
      "id": "10060",
      "modell_id": "30862",
      "c_merke": "SUZUKI",
      "c_modell": "GRAND VITARA",
      "c_typ": "2.0 HDI 110 4x4",
      "slug": "20-hdi-110-4x4",
      "yearRange": "2001 - 2005",
      "registeredCars": "40",
      "seats": "1-4",
      "imageUrl": "https://cdn.bilregistret.ai/compressed-mobile/Bilregistret-suzuki-grand vitara-2001-2005.webp",
      "C_chassi": "[FT, HT]",
      "engine": "DIESEL",
      "originalData": {
        "ID": "10060",
        "submodel_title": "2-0-HDI-110-4x4-TERRANGBIL-FT-HT-FYRHJULSDRIFT-80-kw",
        "modell_id": "30862",
        "C_merke": "SUZUKI",
        "C_modell": "GRAND VITARA",
        "C_typ": "2.0 HDI 110 4x4",
        "slug": "2.0-hdi-110-4x4",
        "ar_fra": "2001",
        "ar_till": "2005",
        "t_count": "40",
        "Car Image": "https://cdn.bilregistret.ai/compressed-mobile/Bilregistret-suzuki-grand vitara-2001-2005.webp",
        "high_res": "https://cdn.bilregistret.ai/high-res/bilregistret-suzuki-grand-vitara-2009-2024.webp",
        "C_chassi": "[FT, HT]",
        "C_bransle": "DIESEL",
        "C_kaross": "TERRÄNGBIL",
        "C_hk": "109",
        "minSeats": "1",
        "maxSeats": "4"
      }
    },
    {
      "id": "6817",
      "modell_id": "30862",
      "c_merke": "SUZUKI",
      "c_modell": "GRAND VITARA",
      "c_typ": "2.0 HDI 110 16V 4x4",
      "slug": "20-hdi-110-16v-4x4",
      "yearRange": "2001 - 2005",
      "registeredCars": "101",
      "seats": "1-6",
      "imageUrl": "https://cdn.bilregistret.ai/compressed-mobile/Bilregistret-suzuki-grand-vitara-2001-2005.webp",
      "C_chassi": "[FT, HT]",
      "engine": "DIESEL",
      "originalData": {
        "ID": "6817",
        "submodel_title": "2-0-HDI-110-16V-4x4-TERRANGBIL-FT-HT-FYRHJULSDRIFT-80-kw",
        "modell_id": "30862",
        "C_merke": "SUZUKI",
        "C_modell": "GRAND VITARA",
        "C_typ": "2.0 HDI 110 16V 4x4",
        "slug": "2.0-hdi-110-16v-4x4",
        "ar_fra": "2001",
        "ar_till": "2005",
        "t_count": "101",
        "Car Image": "https://cdn.bilregistret.ai/compressed-mobile/Bilregistret-suzuki-grand-vitara-2001-2005.webp",
        "high_res": "https://cdn.bilregistret.ai/high-res/bilregistret-suzuki-grand-vitara-2009-2024.webp",
        "C_chassi": "[FT, HT]",
        "C_bransle": "DIESEL",
        "C_kaross": "TERRÄNGBIL",
        "C_hk": "109",
        "minSeats": "1",
        "maxSeats": "6"
      }
    },
    {
      "id": "15121",
      "modell_id": "30862",
      "c_merke": "SUZUKI",
      "c_modell": "GRAND VITARA",
      "c_typ": "1.6 4x4",
      "slug": "16-4x4",
      "yearRange": "1998 - 2003",
      "registeredCars": "5",
      "seats": "3-3",
      "imageUrl": "https://cdn.bilregistret.ai/compressed-mobile/Bilregistret-suzuki-grand-vitara-1998-2003.webp",
      "C_chassi": "[FT, HT]",
      "engine": "BENSIN",
      "originalData": {
        "ID": "15121",
        "submodel_title": "1-6-4x4-TERRANGBIL-FT-HT-FYRHJULSDRIFT-69-kw",
        "modell_id": "30862",
        "C_merke": "SUZUKI",
        "C_modell": "GRAND VITARA",
        "C_typ": "1.6 4x4",
        "slug": "1.6-4x4",
        "ar_fra": "1998",
        "ar_till": "2003",
        "t_count": "5",
        "Car Image": "https://cdn.bilregistret.ai/compressed-mobile/Bilregistret-suzuki-grand-vitara-1998-2003.webp",
        "high_res": "https://cdn.bilregistret.ai/high-res/bilregistret-suzuki-grand-vitara-2009-2024.webp",
        "C_chassi": "[FT, HT]",
        "C_bransle": "BENSIN",
        "C_kaross": "TERRÄNGBIL",
        "C_hk": "94",
        "minSeats": "3",
        "maxSeats": "3"
      }
    },
    {
      "id": "2001",
      "modell_id": "30862",
      "c_merke": "SUZUKI",
      "c_modell": "GRAND VITARA",
      "c_typ": "2.7 4x4",
      "slug": "27-4x4",
      "yearRange": "2001 - 2003",
      "registeredCars": "677",
      "seats": "1-6",
      "imageUrl": "https://cdn.bilregistret.ai/compressed-mobile/Bilregistret-suzuki-grand-vitara-2001-2003.webp",
      "C_chassi": "[FT, HT]",
      "engine": "BENSIN",
      "originalData": {
        "ID": "2001",
        "submodel_title": "2-7-4x4-TERRANGBIL-FT-HT-FYRHJULSDRIFT-127-kw",
        "modell_id": "30862",
        "C_merke": "SUZUKI",
        "C_modell": "GRAND VITARA",
        "C_typ": "2.7 4x4",
        "slug": "2.7-4x4",
        "ar_fra": "2001",
        "ar_till": "2003",
        "t_count": "677",
        "Car Image": "https://cdn.bilregistret.ai/compressed-mobile/Bilregistret-suzuki-grand-vitara-2001-2003.webp",
        "high_res": "https://cdn.bilregistret.ai/high-res/bilregistret-suzuki-grand-vitara-2009-2024.webp",
        "C_chassi": "[FT, HT]",
        "C_bransle": "BENSIN",
        "C_kaross": "TERRÄNGBIL",
        "C_hk": "173",
        "minSeats": "1",
        "maxSeats": "6"
      }
    },
    {
      "id": "7804",
      "modell_id": "30862",
      "c_merke": "SUZUKI",
      "c_modell": "GRAND VITARA",
      "c_typ": "2.0 TD 4x4",
      "slug": "20-td-4x4",
      "yearRange": "1998 - 2003",
      "registeredCars": "71",
      "seats": "1-4",
      "imageUrl": "https://cdn.bilregistret.ai/compressed-mobile/Bilregistret-suzuki-grand-vitara-1998-2003.webp",
      "C_chassi": "[FT, HT]",
      "engine": "DIESEL",
      "originalData": {
        "ID": "7804",
        "submodel_title": "2-0-TD-4x4-TERRANGBIL-FT-HT-FYRHJULSDRIFT-64-kw",
        "modell_id": "30862",
        "C_merke": "SUZUKI",
        "C_modell": "GRAND VITARA",
        "C_typ": "2.0 TD 4x4",
        "slug": "2.0-td-4x4",
        "ar_fra": "1998",
        "ar_till": "2003",
        "t_count": "71",
        "Car Image": "https://cdn.bilregistret.ai/compressed-mobile/Bilregistret-suzuki-grand-vitara-1998-2003.webp",
        "high_res": "https://cdn.bilregistret.ai/high-res/bilregistret-suzuki-grand-vitara-2009-2024.webp",
        "C_chassi": "[FT, HT]",
        "C_bransle": "DIESEL",
        "C_kaross": "TERRÄNGBIL",
        "C_hk": "87",
        "minSeats": "1",
        "maxSeats": "4"
      }
    },
    {
      "id": "2391",
      "modell_id": "30862",
      "c_merke": "SUZUKI",
      "c_modell": "GRAND VITARA",
      "c_typ": "2.0 4x4",
      "slug": "20-4x4",
      "yearRange": "1998 - 2003",
      "registeredCars": "544",
      "seats": "1-4",
      "imageUrl": "wix:image://v1/fc9b98_13bd2cd2f27345e3aec6e562eab6baab~mv2.webp/2-0-4x4-terrangbil-ft-ht-fyrhjulsdrift-94-kw.png#originwidth=1360&originheight=768",
      "C_chassi": "[FT, HT]",
      "engine": "BENSIN",
      "originalData": {
        "ID": "2391",
        "submodel_title": "2-0-4x4-TERRANGBIL-FT-HT-FYRHJULSDRIFT-94-kw",
        "modell_id": "30862",
        "C_merke": "SUZUKI",
        "C_modell": "GRAND VITARA",
        "C_typ": "2.0 4x4",
        "slug": "2.0-4x4",
        "ar_fra": "1998",
        "ar_till": "2003",
        "t_count": "544",
        "Car Image": "wix:image://v1/fc9b98_13bd2cd2f27345e3aec6e562eab6baab~mv2.webp/2-0-4x4-terrangbil-ft-ht-fyrhjulsdrift-94-kw.png#originwidth=1360&originheight=768",
        "high_res": "https://cdn.bilregistret.ai/high-res/bilregistret-suzuki-grand-vitara-2009-2024.webp",
        "C_chassi": "[FT, HT]",
        "C_bransle": "BENSIN",
        "C_kaross": "TERRÄNGBIL",
        "C_hk": "128",
        "minSeats": "1",
        "maxSeats": "4"
      }
    },
    {
      "id": "7289",
      "modell_id": "30862",
      "c_merke": "SUZUKI",
      "c_modell": "GRAND VITARA",
      "c_typ": "1.6 4x4",
      "slug": "16-4x4",
      "yearRange": "1998 - 2003",
      "registeredCars": "87",
      "seats": "1-4",
      "imageUrl": "https://cdn.bilregistret.ai/compressed-mobile/Bilregistret-suzuki-grand-vitara-1998-2003.webp",
      "C_chassi": "[GT]",
      "engine": "BENSIN",
      "originalData": {
        "ID": "7289",
        "submodel_title": "1-6-4x4-CABRIOLET-GT-FYRHJULSDRIFT-69-kw",
        "modell_id": "30862",
        "C_merke": "SUZUKI",
        "C_modell": "GRAND VITARA",
        "C_typ": "1.6 4x4",
        "slug": "1.6-4x4",
        "ar_fra": "1998",
        "ar_till": "2003",
        "t_count": "87",
        "Car Image": "https://cdn.bilregistret.ai/compressed-mobile/Bilregistret-suzuki-grand-vitara-1998-2003.webp",
        "high_res": "https://cdn.bilregistret.ai/high-res/bilregistret-suzuki-grand-vitara-2009-2024.webp",
        "C_chassi": "[GT]",
        "C_bransle": "BENSIN",
        "C_kaross": "CABRIOLET",
        "C_hk": "94",
        "minSeats": "1",
        "maxSeats": "4"
      }
    },
    {
      "id": "2556",
      "modell_id": "30862",
      "c_merke": "SUZUKI",
      "c_modell": "GRAND VITARA",
      "c_typ": "2.7 4x4",
      "slug": "27-4x4",
      "yearRange": "2003 - 2003",
      "registeredCars": "494",
      "seats": "1-6",
      "imageUrl": "https://cdn.bilregistret.ai/compressed-mobile/Bilregistret-suzuki-grand-vitara-2003-2003.webp",
      "C_chassi": "[FT, HT]",
      "engine": "BENSIN",
      "originalData": {
        "ID": "2556",
        "submodel_title": "2-7-4x4-TERRANGBIL-FT-HT-FYRHJULSDRIFT-135-kw",
        "modell_id": "30862",
        "C_merke": "SUZUKI",
        "C_modell": "GRAND VITARA",
        "C_typ": "2.7 4x4",
        "slug": "2.7-4x4",
        "ar_fra": "2003",
        "ar_till": "2003",
        "t_count": "494",
        "Car Image": "https://cdn.bilregistret.ai/compressed-mobile/Bilregistret-suzuki-grand-vitara-2003-2003.webp",
        "high_res": "https://cdn.bilregistret.ai/high-res/bilregistret-suzuki-grand-vitara-2009-2024.webp",
        "C_chassi": "[FT, HT]",
        "C_bransle": "BENSIN",
        "C_kaross": "TERRÄNGBIL",
        "C_hk": "184",
        "minSeats": "1",
        "maxSeats": "6"
      }
    },
    {
      "id": "14655",
      "modell_id": "30862",
      "c_merke": "SUZUKI",
      "c_modell": "GRAND VITARA",
      "c_typ": "2.0 4x4",
      "slug": "20-4x4",
      "yearRange": "1998 - 2003",
      "registeredCars": "7",
      "seats": "1-3",
      "imageUrl": "https://cdn.bilregistret.ai/compressed-mobile/Bilregistret-suzuki-grand-vitara-1998-2003.webp",
      "C_chassi": "[GT]",
      "engine": "BENSIN",
      "originalData": {
        "ID": "14655",
        "submodel_title": "2-0-4x4-CABRIOLET-GT-FYRHJULSDRIFT-94-kw",
        "modell_id": "30862",
        "C_merke": "SUZUKI",
        "C_modell": "GRAND VITARA",
        "C_typ": "2.0 4x4",
        "slug": "2.0-4x4",
        "ar_fra": "1998",
        "ar_till": "2003",
        "t_count": "7",
        "Car Image": "https://cdn.bilregistret.ai/compressed-mobile/Bilregistret-suzuki-grand-vitara-1998-2003.webp",
        "high_res": "https://cdn.bilregistret.ai/high-res/bilregistret-suzuki-grand-vitara-2009-2024.webp",
        "C_chassi": "[GT]",
        "C_bransle": "BENSIN",
        "C_kaross": "CABRIOLET",
        "C_hk": "128",
        "minSeats": "1",
        "maxSeats": "3"
      }
    },
    {
      "id": "2510",
      "modell_id": "30862",
      "c_merke": "SUZUKI",
      "c_modell": "GRAND VITARA",
      "c_typ": "2.5 V6 24V 4x4",
      "slug": "25-v6-24v-4x4",
      "yearRange": "2001 - 2003",
      "registeredCars": "507",
      "seats": "1-4",
      "imageUrl": "https://cdn.bilregistret.ai/compressed-mobile/Bilregistret-suzuki-grand-vitara-2001-2003.webp",
      "C_chassi": "[FT, HT]",
      "engine": "BENSIN",
      "originalData": {
        "ID": "2510",
        "submodel_title": "2-5-V6-24V-4x4-TERRANGBIL-FT-HT-FYRHJULSDRIFT-116-kw",
        "modell_id": "30862",
        "C_merke": "SUZUKI",
        "C_modell": "GRAND VITARA",
        "C_typ": "2.5 V6 24V 4x4",
        "slug": "2.5-v6-24v-4x4",
        "ar_fra": "2001",
        "ar_till": "2003",
        "t_count": "507",
        "Car Image": "https://cdn.bilregistret.ai/compressed-mobile/Bilregistret-suzuki-grand-vitara-2001-2003.webp",
        "high_res": "https://cdn.bilregistret.ai/high-res/bilregistret-suzuki-grand-vitara-2009-2024.webp",
        "C_chassi": "[FT, HT]",
        "C_bransle": "BENSIN",
        "C_kaross": "TERRÄNGBIL",
        "C_hk": "158",
        "minSeats": "1",
        "maxSeats": "4"
      }
    },
    {
      "id": "2328",
      "modell_id": "30862",
      "c_merke": "SUZUKI",
      "c_modell": "GRAND VITARA",
      "c_typ": "2.5 V6 24V 4x4",
      "slug": "25-v6-24v-4x4",
      "yearRange": "1998 - 2003",
      "registeredCars": "547",
      "seats": "1-4",
      "imageUrl": "https://cdn.bilregistret.ai/compressed-mobile/Bilregistret-suzuki-grand-vitara-1998-2003.webp",
      "C_chassi": "[FT, HT]",
      "engine": "BENSIN",
      "originalData": {
        "ID": "2328",
        "submodel_title": "2-5-V6-24V-4x4-TERRANGBIL-FT-HT-FYRHJULSDRIFT-106-kw",
        "modell_id": "30862",
        "C_merke": "SUZUKI",
        "C_modell": "GRAND VITARA",
        "C_typ": "2.5 V6 24V 4x4",
        "slug": "2.5-v6-24v-4x4",
        "ar_fra": "1998",
        "ar_till": "2003",
        "t_count": "547",
        "Car Image": "https://cdn.bilregistret.ai/compressed-mobile/Bilregistret-suzuki-grand-vitara-1998-2003.webp",
        "high_res": "https://cdn.bilregistret.ai/high-res/bilregistret-suzuki-grand-vitara-2009-2024.webp",
        "C_chassi": "[FT, HT]",
        "C_bransle": "BENSIN",
        "C_kaross": "TERRÄNGBIL",
        "C_hk": "144",
        "minSeats": "1",
        "maxSeats": "4"
      }
    }
  ]
}