{
  "brand": {
    "id": "572",
    "merke_id": "108",
    "title": "Nissan",
    "slug": "nissan",
    "brandimage": "https://cdn.bilregistret.ai/brands/nissan.png",
    "bannerimage": "https://cdn.bilregistret.ai/brands/nissan-car.jpeg",
    "country_code": "Japan",
    "flags": "https://d220xhopowubtq.cloudfront.net/flags/Group.svg",
    "originalData": {
      "id": "572",
      "merke_id": "108",
      "title": "Nissan",
      "slug": "nissan",
      "brandimage": "https://cdn.bilregistret.ai/brands/nissan.png",
      "bannerimage": "https://cdn.bilregistret.ai/brands/nissan-car.jpeg",
      "country_code": "Japan",
      "flags": "https://d220xhopowubtq.cloudfront.net/flags/Group.svg",
      "brands_list": "/bil/",
      "brands_item": "/bil/nissan",
      "view_count": "21"
    }
  },
  "model": {
    "id": "20569",
    "c_merke": "NISSAN",
    "c_modell": "URVAN",
    "slug": "urvan",
    "yearRange": "1981-1997",
    "registeredCars": "0",
    "seats": "0-0",
    "imageUrl": "https://cdn.bilregistret.ai/compressed-mobile/Bilregistret-nissan-urvan-1988-1997.webp",
    "fuelTypes": [
      "BENSIN",
      "DIESEL"
    ],
    "bodyTypes": [
      "BUSS",
      "SKÅP"
    ],
    "engineTypes": [
      "BAKHJULSDRIFT"
    ],
    "minYear": 1981,
    "maxYear": 1997,
    "originalData": {
      "ID": "20569",
      "C_merke": "NISSAN",
      "C_modell": "URVAN",
      "slug": "urvan",
      "modell_id": "10720",
      "MINI_AR": "1981",
      "MAX_YEAR": "1997",
      "Car Image": "https://cdn.bilregistret.ai/compressed-mobile/Bilregistret-nissan-urvan-1988-1997.webp",
      "high_res": "https://cdn.bilregistret.ai/high-res/bilregistret-nissan-urvan-1988-1997.webp",
      "BRANSLE_SAMLAD": "BENSIN, DIESEL",
      "kaross_samlad": "BUSS, SKÅP",
      "HJUL_DRIFT_SAMLAD": "BAKHJULSDRIFT"
    }
  },
  "subModels": [
    {
      "id": "20572",
      "modell_id": "10720",
      "c_merke": "NISSAN",
      "c_modell": "URVAN",
      "c_typ": "2.3 D",
      "slug": "23-d",
      "yearRange": "1988 - 1997",
      "registeredCars": "0",
      "seats": "0-0",
      "imageUrl": "https://cdn.bilregistret.ai/compressed-mobile/Bilregistret-nissan-urvan-1988-1997.webp",
      "C_chassi": "[E24]",
      "engine": "DIESEL",
      "originalData": {
        "ID": "20572",
        "submodel_title": "2-3-D-SKAP-E24-BAKHJULSDRIFT-51-kw",
        "modell_id": "10720",
        "C_merke": "NISSAN",
        "C_modell": "URVAN",
        "C_typ": "2.3 D",
        "slug": "2.3-d",
        "ar_fra": "1988",
        "ar_till": "1997",
        "Car Image": "https://cdn.bilregistret.ai/compressed-mobile/Bilregistret-nissan-urvan-1988-1997.webp",
        "high_res": "https://cdn.bilregistret.ai/high-res/bilregistret-nissan-urvan-1988-1997.webp",
        "C_chassi": "[E24]",
        "C_bransle": "DIESEL",
        "C_kaross": "SKÅP",
        "C_hk": "69"
      }
    },
    {
      "id": "20569",
      "modell_id": "10720",
      "c_merke": "NISSAN",
      "c_modell": "URVAN",
      "c_typ": "2.5 D",
      "slug": "25-d",
      "yearRange": "1988 - 1997",
      "registeredCars": "0",
      "seats": "0-0",
      "imageUrl": "https://cdn.bilregistret.ai/compressed-mobile/Bilregistret-nissan-urvan-1988-1997.webp",
      "C_chassi": "[E24]",
      "engine": "DIESEL",
      "originalData": {
        "ID": "20569",
        "submodel_title": "2-5-D-SKAP-E24-BAKHJULSDRIFT-59-kw",
        "modell_id": "10720",
        "C_merke": "NISSAN",
        "C_modell": "URVAN",
        "C_typ": "2.5 D",
        "slug": "2.5-d",
        "ar_fra": "1988",
        "ar_till": "1997",
        "Car Image": "https://cdn.bilregistret.ai/compressed-mobile/Bilregistret-nissan-urvan-1988-1997.webp",
        "high_res": "https://cdn.bilregistret.ai/high-res/bilregistret-nissan-urvan-1988-1997.webp",
        "C_chassi": "[E24]",
        "C_bransle": "DIESEL",
        "C_kaross": "SKÅP",
        "C_hk": "80"
      }
    },
    {
      "id": "17744",
      "modell_id": "10720",
      "c_merke": "NISSAN",
      "c_modell": "URVAN",
      "c_typ": "2",
      "slug": "2",
      "yearRange": "1987 - 1997",
      "registeredCars": "1",
      "seats": "1-1",
      "imageUrl": "https://cdn.bilregistret.ai/compressed-mobile/Bilregistret-nissan-urvan-1987-1997.webp",
      "C_chassi": "[E24]",
      "engine": "BENSIN",
      "originalData": {
        "ID": "17744",
        "submodel_title": "2-0-SKAP-E24-BAKHJULSDRIFT-64-kw",
        "modell_id": "10720",
        "C_merke": "NISSAN",
        "C_modell": "URVAN",
        "C_typ": "2",
        "slug": "2",
        "ar_fra": "1987",
        "ar_till": "1997",
        "t_count": "1",
        "Car Image": "https://cdn.bilregistret.ai/compressed-mobile/Bilregistret-nissan-urvan-1987-1997.webp",
        "high_res": "https://cdn.bilregistret.ai/high-res/bilregistret-nissan-urvan-1988-1997.webp",
        "C_chassi": "[E24]",
        "C_bransle": "BENSIN",
        "C_kaross": "SKÅP",
        "C_hk": "87",
        "minSeats": "1",
        "maxSeats": "1"
      }
    },
    {
      "id": "20902",
      "modell_id": "10720",
      "c_merke": "NISSAN",
      "c_modell": "URVAN",
      "c_typ": "2.5 D",
      "slug": "25-d",
      "yearRange": "1989 - 1996",
      "registeredCars": "0",
      "seats": "0-0",
      "imageUrl": "https://cdn.bilregistret.ai/compressed-mobile/Bilregistret-nissan-urvan-1989-1996.webp",
      "C_chassi": "[E24]",
      "engine": "DIESEL",
      "originalData": {
        "ID": "20902",
        "submodel_title": "2-5-D-BUSS-E24-BAKHJULSDRIFT-59-kw",
        "modell_id": "10720",
        "C_merke": "NISSAN",
        "C_modell": "URVAN",
        "C_typ": "2.5 D",
        "slug": "2.5-d",
        "ar_fra": "1989",
        "ar_till": "1996",
        "Car Image": "https://cdn.bilregistret.ai/compressed-mobile/Bilregistret-nissan-urvan-1989-1996.webp",
        "high_res": "https://cdn.bilregistret.ai/high-res/bilregistret-nissan-urvan-1988-1997.webp",
        "C_chassi": "[E24]",
        "C_bransle": "DIESEL",
        "C_kaross": "BUSS",
        "C_hk": "80"
      }
    },
    {
      "id": "20092",
      "modell_id": "10720",
      "c_merke": "NISSAN",
      "c_modell": "URVAN",
      "c_typ": "2",
      "slug": "2",
      "yearRange": "1986 - 1994",
      "registeredCars": "0",
      "seats": "0-0",
      "imageUrl": "https://cdn.bilregistret.ai/compressed-mobile/Bilregistret-nissan-urvan-1986-1994.webp",
      "C_chassi": "[E24]",
      "engine": "BENSIN",
      "originalData": {
        "ID": "20092",
        "submodel_title": "2-BUSS-E24-BAKHJULSDRIFT-65-kw",
        "modell_id": "10720",
        "C_merke": "NISSAN",
        "C_modell": "URVAN",
        "C_typ": "2",
        "slug": "2",
        "ar_fra": "1986",
        "ar_till": "1994",
        "Car Image": "https://cdn.bilregistret.ai/compressed-mobile/Bilregistret-nissan-urvan-1986-1994.webp",
        "high_res": "https://cdn.bilregistret.ai/high-res/bilregistret-nissan-urvan-1988-1997.webp",
        "C_chassi": "[E24]",
        "C_bransle": "BENSIN",
        "C_kaross": "BUSS",
        "C_hk": "88"
      }
    },
    {
      "id": "10322",
      "modell_id": "10720",
      "c_merke": "NISSAN",
      "c_modell": "URVAN",
      "c_typ": "2.4 i",
      "slug": "24-i",
      "yearRange": "1989 - 1993",
      "registeredCars": "34",
      "seats": "1-7",
      "imageUrl": "https://cdn.bilregistret.ai/compressed-mobile/Bilregistret-nissan-urvan-1989-1993.webp",
      "C_chassi": "[E24]",
      "engine": "BENSIN",
      "originalData": {
        "ID": "10322",
        "submodel_title": "2-4-i-BUSS-E24-BAKHJULSDRIFT-74-kw",
        "modell_id": "10720",
        "C_merke": "NISSAN",
        "C_modell": "URVAN",
        "C_typ": "2.4 i",
        "slug": "2.4-i",
        "ar_fra": "1989",
        "ar_till": "1993",
        "t_count": "34",
        "Car Image": "https://cdn.bilregistret.ai/compressed-mobile/Bilregistret-nissan-urvan-1989-1993.webp",
        "high_res": "https://cdn.bilregistret.ai/high-res/bilregistret-nissan-urvan-1988-1997.webp",
        "C_chassi": "[E24]",
        "C_bransle": "BENSIN",
        "C_kaross": "BUSS",
        "C_hk": "101",
        "minSeats": "1",
        "maxSeats": "7"
      }
    },
    {
      "id": "15093",
      "modell_id": "10720",
      "c_merke": "NISSAN",
      "c_modell": "URVAN",
      "c_typ": "2",
      "slug": "2",
      "yearRange": "1982 - 1988",
      "registeredCars": "5",
      "seats": "1-1",
      "imageUrl": "https://cdn.bilregistret.ai/compressed-mobile/Bilregistret-nissan-urvan-1982-1988.webp",
      "C_chassi": "[E23]",
      "engine": "BENSIN",
      "originalData": {
        "ID": "15093",
        "submodel_title": "2-0-BUSS-E23-BAKHJULSDRIFT-64-kw",
        "modell_id": "10720",
        "C_merke": "NISSAN",
        "C_modell": "URVAN",
        "C_typ": "2",
        "slug": "2",
        "ar_fra": "1982",
        "ar_till": "1988",
        "t_count": "5",
        "Car Image": "https://cdn.bilregistret.ai/compressed-mobile/Bilregistret-nissan-urvan-1982-1988.webp",
        "high_res": "https://cdn.bilregistret.ai/high-res/bilregistret-nissan-urvan-1988-1997.webp",
        "C_chassi": "[E23]",
        "C_bransle": "BENSIN",
        "C_kaross": "BUSS",
        "C_hk": "87",
        "minSeats": "1",
        "maxSeats": "1"
      }
    },
    {
      "id": "12340",
      "modell_id": "10720",
      "c_merke": "NISSAN",
      "c_modell": "URVAN",
      "c_typ": "2.3 D",
      "slug": "23-d",
      "yearRange": "1982 - 1987",
      "registeredCars": "18",
      "seats": "1-4",
      "imageUrl": "https://cdn.bilregistret.ai/compressed-mobile/Bilregistret-nissan-urvan-1982-1987.webp",
      "C_chassi": "[E23]",
      "engine": "DIESEL",
      "originalData": {
        "ID": "12340",
        "submodel_title": "2-3-D-SKAP-E23-BAKHJULSDRIFT-50-kw",
        "modell_id": "10720",
        "C_merke": "NISSAN",
        "C_modell": "URVAN",
        "C_typ": "2.3 D",
        "slug": "2.3-d",
        "ar_fra": "1982",
        "ar_till": "1987",
        "t_count": "18",
        "Car Image": "https://cdn.bilregistret.ai/compressed-mobile/Bilregistret-nissan-urvan-1982-1987.webp",
        "high_res": "https://cdn.bilregistret.ai/high-res/bilregistret-nissan-urvan-1988-1997.webp",
        "C_chassi": "[E23]",
        "C_bransle": "DIESEL",
        "C_kaross": "SKÅP",
        "C_hk": "68",
        "minSeats": "1",
        "maxSeats": "4"
      }
    },
    {
      "id": "20724",
      "modell_id": "10720",
      "c_merke": "NISSAN",
      "c_modell": "URVAN",
      "c_typ": "2.2 D",
      "slug": "22-d",
      "yearRange": "1981 - 1982",
      "registeredCars": "0",
      "seats": "0-0",
      "imageUrl": "https://cdn.bilregistret.ai/compressed-mobile/Bilregistret-nissan-urvan-1981-1982.webp",
      "C_chassi": "[E23]",
      "engine": "DIESEL",
      "originalData": {
        "ID": "20724",
        "submodel_title": "2-2-D-SKAP-E23-BAKHJULSDRIFT-47-kw",
        "modell_id": "10720",
        "C_merke": "NISSAN",
        "C_modell": "URVAN",
        "C_typ": "2.2 D",
        "slug": "2.2-d",
        "ar_fra": "1981",
        "ar_till": "1982",
        "Car Image": "https://cdn.bilregistret.ai/compressed-mobile/Bilregistret-nissan-urvan-1981-1982.webp",
        "high_res": "https://cdn.bilregistret.ai/high-res/bilregistret-nissan-urvan-1988-1997.webp",
        "C_chassi": "[E23]",
        "C_bransle": "DIESEL",
        "C_kaross": "SKÅP",
        "C_hk": "64"
      }
    }
  ]
}