{
  "brand": {
    "id": "493",
    "merke_id": "123",
    "title": "MERCEDES BENZ",
    "slug": "mercedes-benz",
    "brandimage": "https://cdn.bilregistret.ai/brands/mercedes.png",
    "bannerimage": "https://cdn.bilregistret.ai/brands/mercedes-car.webp",
    "country_code": "Germany",
    "flags": "https://d220xhopowubtq.cloudfront.net/flags/DE - Germany.svg",
    "originalData": {
      "id": "493",
      "merke_id": "123",
      "title": "MERCEDES BENZ",
      "slug": "mercedes-benz",
      "brandimage": "https://cdn.bilregistret.ai/brands/mercedes.png",
      "bannerimage": "https://cdn.bilregistret.ai/brands/mercedes-car.webp",
      "country_code": "Germany",
      "flags": "https://d220xhopowubtq.cloudfront.net/flags/DE - Germany.svg",
      "brands_list": "/bil/",
      "brands_item": "/bil/mercedes",
      "view_count": "215"
    }
  },
  "model": {
    "id": "3315",
    "c_merke": "MERCEDES BENZ",
    "c_modell": "GLB",
    "slug": "glb",
    "yearRange": "2019-2024",
    "registeredCars": "400",
    "seats": "4-6",
    "imageUrl": "https://cdn.bilregistret.ai/compressed-mobile/Bilregistret-mercedes-glb-2019-2024.webp",
    "fuelTypes": [
      "BENSIN",
      "DIESEL"
    ],
    "bodyTypes": [
      "SUV"
    ],
    "engineTypes": [
      "FRAMHJULSDRIFT",
      "FYRHJULSDRIFT"
    ],
    "minYear": 2019,
    "maxYear": 2024,
    "originalData": {
      "ID": "3315",
      "C_merke": "MERCEDES BENZ",
      "C_modell": "GLB",
      "slug": "glb",
      "modell_id": "137600",
      "MINI_AR": "2019",
      "MAX_YEAR": "2024",
      "t_count": "400",
      "Car Image": "https://cdn.bilregistret.ai/compressed-mobile/Bilregistret-mercedes-glb-2019-2024.webp",
      "high_res": "https://cdn.bilregistret.ai/high-res/bilregistret-mercedes-benz-glb-2019-2024.webp",
      "BRANSLE_SAMLAD": "BENSIN, DIESEL",
      "kaross_samlad": "SUV",
      "HJUL_DRIFT_SAMLAD": "FRAMHJULSDRIFT, FYRHJULSDRIFT",
      "minSeats": "4",
      "maxSeats": "6"
    }
  },
  "subModel": {
    "id": "5048",
    "modell_id": "137600",
    "c_merke": "MERCEDES BENZ",
    "c_modell": "GLB",
    "c_typ": "200",
    "slug": "200",
    "yearRange": "2019 - 2024",
    "registeredCars": "426",
    "seats": "4-6",
    "imageUrl": "https://cdn.bilregistret.ai/compressed-mobile/Bilregistret-mercedes-glb-2019-2024.webp",
    "C_chassi": "[X247]",
    "engine": "BENSIN",
    "originalData": {
      "ID": "5048",
      "submodel_title": "200-SUV-X247-FRAMHJULSDRIFT-120-kw",
      "modell_id": "137600",
      "C_merke": "MERCEDES BENZ",
      "C_modell": "GLB",
      "C_typ": "200",
      "slug": "200",
      "ar_fra": "2019",
      "ar_till": "2024",
      "t_count": "426",
      "Car Image": "https://cdn.bilregistret.ai/compressed-mobile/Bilregistret-mercedes-glb-2019-2024.webp",
      "high_res": "https://cdn.bilregistret.ai/high-res/bilregistret-mercedes-benz-glb-2019-2024.webp",
      "C_chassi": "[X247]",
      "C_bransle": "BENSIN",
      "C_kaross": "SUV",
      "C_hk": "163",
      "minSeats": "4",
      "maxSeats": "6"
    }
  }
}