{
  "brand": {
    "id": "574",
    "merke_id": "100",
    "title": "Volvo",
    "slug": "volvo",
    "brandimage": "https://cdn.bilregistret.ai/brands/volvo.png",
    "bannerimage": "https://cdn.bilregistret.ai/brands/volvo-car.webp",
    "country_code": "Sweden",
    "flags": "https://d220xhopowubtq.cloudfront.net/flags/SE - Sweden.svg",
    "originalData": {
      "id": "574",
      "merke_id": "100",
      "title": "Volvo",
      "slug": "volvo",
      "brandimage": "https://cdn.bilregistret.ai/brands/volvo.png",
      "bannerimage": "https://cdn.bilregistret.ai/brands/volvo-car.webp",
      "country_code": "Sweden",
      "flags": "https://d220xhopowubtq.cloudfront.net/flags/SE - Sweden.svg",
      "brands_list": "/bil/",
      "brands_item": "/bil/volvo",
      "view_count": "555"
    }
  },
  "model": {
    "id": "1373",
    "c_merke": "VOLVO",
    "c_modell": "S80",
    "slug": "s80",
    "yearRange": "1998-2024",
    "registeredCars": "1030",
    "seats": "1-4",
    "imageUrl": "https://cdn.bilregistret.ai/compressed-mobile/Bilregistret-volvo-s80-2006-2024.webp",
    "fuelTypes": [
      "BENSIN",
      "BENSIN/ETANOL",
      "BENSIN/NATURGAS (CNG)",
      "DIESEL"
    ],
    "bodyTypes": [
      "SEDAN"
    ],
    "engineTypes": [
      "FRAMHJULSDRIFT",
      "FYRHJULSDRIFT"
    ],
    "minYear": 1998,
    "maxYear": 2024,
    "originalData": {
      "ID": "1373",
      "C_merke": "VOLVO",
      "C_modell": "S80",
      "slug": "s80",
      "modell_id": "19336",
      "MINI_AR": "1998",
      "MAX_YEAR": "2024",
      "t_count": "1030",
      "Car Image": "https://cdn.bilregistret.ai/compressed-mobile/Bilregistret-volvo-s80-2006-2024.webp",
      "high_res": "https://cdn.bilregistret.ai/high-res/bilregistret-volvo-s80-2006-2024.webp",
      "BRANSLE_SAMLAD": "BENSIN, BENSIN/ETANOL, BENSIN/NATURGAS (CNG), DIESEL",
      "kaross_samlad": "SEDAN",
      "HJUL_DRIFT_SAMLAD": "FRAMHJULSDRIFT, FYRHJULSDRIFT",
      "minSeats": "1",
      "maxSeats": "4"
    }
  },
  "subModel": {
    "id": "4099",
    "modell_id": "19336",
    "c_merke": "VOLVO",
    "c_modell": "S80",
    "c_typ": "1.6 D DRIVe",
    "slug": "16-d-drive",
    "yearRange": "2010 - 2011",
    "registeredCars": "263",
    "seats": "4-4",
    "imageUrl": "https://cdn.bilregistret.ai/compressed-mobile/Bilregistret-volvo-s80-2010-2011.webp",
    "C_chassi": "[124]",
    "engine": "DIESEL",
    "originalData": {
      "ID": "4099",
      "submodel_title": "1-6-D-DRIVe-SEDAN-124-FRAMHJULSDRIFT-80-kw",
      "modell_id": "19336",
      "C_merke": "VOLVO",
      "C_modell": "S80",
      "C_typ": "1.6 D DRIVe",
      "slug": "1.6-d-drive",
      "ar_fra": "2010",
      "ar_till": "2011",
      "t_count": "263",
      "Car Image": "https://cdn.bilregistret.ai/compressed-mobile/Bilregistret-volvo-s80-2010-2011.webp",
      "high_res": "https://cdn.bilregistret.ai/high-res/bilregistret-volvo-s80-2006-2024.webp",
      "C_chassi": "[124]",
      "C_bransle": "DIESEL",
      "C_kaross": "SEDAN",
      "C_hk": "109",
      "minSeats": "4",
      "maxSeats": "4"
    }
  }
}